taptaptap3/__init__.py
taptaptap3/__main__.py
taptaptap3/api.py
taptaptap3/exc.py
taptaptap3/impl.py
taptaptap3/proc.py
taptaptap3/bin/__init__.py
taptaptap3/bin/tapmerge.py
taptaptap3/bin/tapvalidate.py
taptaptap3-3.1.0.dist-info/METADATA
taptaptap3-3.1.0.dist-info/WHEEL
taptaptap3-3.1.0.dist-info/entry_points.txt
taptaptap3-3.1.0.dist-info/licenses/LICENSE
taptaptap3-3.1.0.dist-info/RECORD
