Metadata-Version: 2.3
Name: taptaptap3
Version: 3.1.0
Summary: Test Anything Protocol handling for cats
Project-URL: Homepage, http://lukas-prokop.at/proj/taptaptap/
Author-email: Lukas Prokop <admin@lukas-prokop.at>
License-File: LICENSE
Keywords: TAP,test-anything-protocol,testing
Classifier: Development Status :: 5 - Production/Stable
Classifier: Environment :: Console
Classifier: Intended Audience :: Developers
Classifier: Intended Audience :: Information Technology
Classifier: License :: OSI Approved :: BSD License
Classifier: Natural Language :: English
Classifier: Operating System :: OS Independent
Classifier: Programming Language :: Python :: 3.5
Classifier: Programming Language :: Python :: 3.6
Classifier: Topic :: Software Development :: Build Tools
Classifier: Topic :: Software Development :: Documentation
Classifier: Topic :: Software Development :: Testing
Classifier: Topic :: System :: Logging
Classifier: Topic :: System :: Systems Administration
Requires-Python: >=3.5
Requires-Dist: pyyaml
